<?xml version="1.0" encoding="UTF-8" ?>
<!DOCTYPE struts PUBLIC
    "-//Apache Software Foundation//DTD Struts Configuration 2.3//EN"
    "http://struts.apache.org/dtds/struts-2.3.dtd">

<struts>
<package name="reddereIusInfo" namespace="/" extends="struts-default">
        <action name="reddereIusInfo_*" class="com.cbd.action.ReddereIusInfoAction" method="{1}">
            <result name="index">/web/page/enterpriseInfo/enforceTheLaw/index.jsp</result>
            <result name="showAdd">/web/page/enterpriseInfo/enforceTheLaw/showAdd.jsp</result>
        </action>
</package>
</struts>
